ppfind/__init__.py
ppfind/cli.py
ppfind/config.py
ppfind/core.py
ppfind-1.1.0.dist-info/licenses/LICENSE
ppfind-1.1.0.dist-info/METADATA
ppfind-1.1.0.dist-info/WHEEL
ppfind-1.1.0.dist-info/entry_points.txt
ppfind-1.1.0.dist-info/top_level.txt
ppfind-1.1.0.dist-info/RECORD
