Metadata-Version: 2.4
Name: ppfind
Version: 1.1.0
Summary: A command-line tool to find paper citations, ArXiv links, and GitHub repository links easily.
Home-page: https://github.com/Disapole-Xiao/ppfind
Author: Disapole
Author-email: disapolexiao@gmail.com
License: MIT
Keywords: papers,citations,arxiv,github,search,cli,api,academic
Classifier: Programming Language :: Python :: 3
Classifier: Operating System :: OS Independent
Requires-Python: >=3.6
License-File: LICENSE
Requires-Dist: pandas
Requires-Dist: requests
Requires-Dist: arxiv
Requires-Dist: google-search-results
Requires-Dist: tqdm
Requires-Dist: openpyxl
Dynamic: author
Dynamic: author-email
Dynamic: classifier
Dynamic: description
Dynamic: description-content-type
Dynamic: home-page
Dynamic: keywords
Dynamic: license
Dynamic: license-file
Dynamic: requires-dist
Dynamic: requires-python
Dynamic: summary
